urltomd
