Metadata-Version: 1.0
Name: urltomd
Version: 0.3
Summary: A library for mapping urls on to markdown files with yaml metadata
Home-page: https://github.com/alexex/urltomd
Author: Alexander Jung-Loddenkemper
Author-email: alexander@julo.ch
License: MIT
Platform: any
